<?xml version="1.0" encoding="UTF-8"?>
<ttFont sfntVersion="\x00\x01\x00\x00" ttLibVersion="4.2">

  <GlyphOrder>
    <!-- The 'id' attribute is only for humans; it is ignored when parsed. -->
    <GlyphID id="0" name=".notdef"/>
    <GlyphID id="1" name="unie478"/>
    <GlyphID id="2" name="unib632"/>
    <GlyphID id="3" name="unif129"/>
    <GlyphID id="4" name="unia618"/>
    <GlyphID id="5" name="unie825"/>
    <GlyphID id="6" name="unia416"/>
    <GlyphID id="7" name="unic541"/>
    <GlyphID id="8" name="unib218"/>
    <GlyphID id="9" name="unib471"/>
    <GlyphID id="10" name="unif254"/>
  </GlyphOrder>

  <head>
    <!-- Most of this table will be recalculated by the compiler -->
    <tableVersion value="1.0"/>
    <fontRevision value="1.0"/>
    <checkSumAdjustment value="0xd9a85eca"/>
    <magicNumber value="0x5f0f3cf5"/>
    <flags value="00000000 00001001"/>
    <unitsPerEm value="1000"/>
    <created value="Sun Oct 13 04:00:31 2019"/>
    <modified value="Wed Mar  3 13:29:00 2021"/>
    <xMin value="10"/>
    <yMin value="-20"/>
    <xMax value="592"/>
    <yMax value="769"/>
    <macStyle value="00000000 00000000"/>
    <lowestRecPPEM value="8"/>
    <fontDirectionHint value="2"/>
    <indexToLocFormat value="0"/>
    <glyphDataFormat value="0"/>
  </head>

  <hhea>
    <tableVersion value="0x00010000"/>
    <ascent value="1060"/>
    <descent value="-340"/>
    <lineGap value="126"/>
    <advanceWidthMax value="600"/>
    <minLeftSideBearing value="0"/>
    <minRightSideBearing value="18"/>
    <xMaxExtent value="582"/>
    <caretSlopeRise value="1"/>
    <caretSlopeRun value="0"/>
    <caretOffset value="0"/>
    <reserved0 value="0"/>
    <reserved1 value="0"/>
    <reserved2 value="0"/>
    <reserved3 value="0"/>
    <metricDataFormat value="0"/>
    <numberOfHMetrics value="2"/>
  </hhea>

  <maxp>
    <!-- Most of this table will be recalculated by the compiler -->
    <tableVersion value="0x10000"/>
    <numGlyphs value="11"/>
    <maxPoints value="57"/>
    <maxContours value="3"/>
    <maxCompositePoints value="0"/>
    <maxCompositeContours value="0"/>
    <maxZones value="2"/>
    <maxTwilightPoints value="0"/>
    <maxStorage value="10"/>
    <maxFunctionDefs value="10"/>
    <maxInstructionDefs value="0"/>
    <maxStackElements value="255"/>
    <maxSizeOfInstructions value="0"/>
    <maxComponentElements value="0"/>
    <maxComponentDepth value="0"/>
  </maxp>

  <OS_2>
    <!-- The fields 'usFirstCharIndex' and 'usLastCharIndex'
         will be recalculated by the compiler -->
    <version value="4"/>
    <xAvgCharWidth value="554"/>
    <usWeightClass value="400"/>
    <usWidthClass value="5"/>
    <fsType value="00000000 00001000"/>
    <ySubscriptXSize value="721"/>
    <ySubscriptYSize value="979"/>
    <ySubscriptXOffset value="0"/>
    <ySubscriptYOffset value="196"/>
    <ySuperscriptXSize value="721"/>
    <ySuperscriptYSize value="979"/>
    <ySuperscriptXOffset value="0"/>
    <ySuperscriptYOffset value="672"/>
    <yStrikeoutSize value="68"/>
    <yStrikeoutPosition value="361"/>
    <sFamilyClass value="0"/>
    <panose>
      <bFamilyType value="2"/>
      <bSerifStyle value="0"/>
      <bWeight value="5"/>
      <bProportion value="3"/>
      <bContrast value="0"/>
      <bStrokeVariation value="0"/>
      <bArmStyle value="0"/>
      <bLetterForm value="0"/>
      <bMidline value="0"/>
      <bXHeight value="0"/>
    </panose>
    <ulUnicodeRange1 value="00000000 00000000 00000000 00000000"/>
    <ulUnicodeRange2 value="00010000 00000000 00000000 00000000"/>
    <ulUnicodeRange3 value="00000000 00000000 00000000 00000000"/>
    <ulUnicodeRange4 value="00000000 00000000 00000000 00000000"/>
    <achVendID value="PfEd"/>
    <fsSelection value="00000000 01000000"/>
    <usFirstCharIndex value="42006"/>
    <usLastCharIndex value="62036"/>
    <sTypoAscender value="1060"/>
    <sTypoDescender value="-340"/>
    <sTypoLineGap value="126"/>
    <usWinAscent value="1060"/>
    <usWinDescent value="340"/>
    <ulCodePageRange1 value="00000000 00000000 00000000 00000001"/>
    <ulCodePageRange2 value="00000000 00000000 00000000 00000000"/>
    <sxHeight value="0"/>
    <sCapHeight value="0"/>
    <usDefaultChar value="0"/>
    <usBreakChar value="32"/>
    <usMaxContext value="0"/>
  </OS_2>

  <hmtx>
    <mtx name=".notdef" width="100" lsb="0"/>
    <mtx name="unia416" width="600" lsb="0"/>
    <mtx name="unia618" width="600" lsb="0"/>
    <mtx name="unib218" width="600" lsb="0"/>
    <mtx name="unib471" width="600" lsb="0"/>
    <mtx name="unib632" width="600" lsb="0"/>
    <mtx name="unic541" width="600" lsb="0"/>
    <mtx name="unie478" width="600" lsb="0"/>
    <mtx name="unie825" width="600" lsb="0"/>
    <mtx name="unif129" width="600" lsb="0"/>
    <mtx name="unif254" width="600" lsb="0"/>
  </hmtx>

  <cmap>
    <tableVersion version="0"/>
    <cmap_format_4 platformID="0" platEncID="3" language="0">
      <map code="0xa416" name="unia416"/><!-- YI SYLLABLE QYRX -->
      <map code="0xa618" name="unia618"/><!-- VAI SYMBOL FAA -->
      <map code="0xb218" name="unib218"/><!-- HANGUL SYLLABLE NUSS -->
      <map code="0xb471" name="unib471"/><!-- HANGUL SYLLABLE DWEONJ -->
      <map code="0xb632" name="unib632"/><!-- HANGUL SYLLABLE DDWANH -->
      <map code="0xc541" name="unic541"/><!-- HANGUL SYLLABLE SSIT -->
      <map code="0xe478" name="unie478"/><!-- ???? -->
      <map code="0xe825" name="unie825"/><!-- ???? -->
      <map code="0xf129" name="unif129"/><!-- ???? -->
      <map code="0xf254" name="unif254"/><!-- ???? -->
    </cmap_format_4>
    <cmap_format_0 platformID="1" platEncID="0" language="0">
    </cmap_format_0>
    <cmap_format_4 platformID="3" platEncID="1" language="0">
      <map code="0xa416" name="unia416"/><!-- YI SYLLABLE QYRX -->
      <map code="0xa618" name="unia618"/><!-- VAI SYMBOL FAA -->
      <map code="0xb218" name="unib218"/><!-- HANGUL SYLLABLE NUSS -->
      <map code="0xb471" name="unib471"/><!-- HANGUL SYLLABLE DWEONJ -->
      <map code="0xb632" name="unib632"/><!-- HANGUL SYLLABLE DDWANH -->
      <map code="0xc541" name="unic541"/><!-- HANGUL SYLLABLE SSIT -->
      <map code="0xe478" name="unie478"/><!-- ???? -->
      <map code="0xe825" name="unie825"/><!-- ???? -->
      <map code="0xf129" name="unif129"/><!-- ???? -->
      <map code="0xf254" name="unif254"/><!-- ???? -->
    </cmap_format_4>
  </cmap>

  <loca>
    <!-- The 'loca' table will be calculated by the compiler -->
  </loca>

  <glyf>

    <!-- The xMin, yMin, xMax and yMax values
         will be recalculated by the compiler. -->

    <TTGlyph name=".notdef" xMin="44" yMin="-20" xMax="57" yMax="41">
      <contour>
        <pt x="44" y="41" on="1"/>
        <pt x="57" y="41" on="1"/>
        <pt x="57" y="-20" on="1"/>
      </contour>
      <instructions/>
    </TTGlyph>

    <TTGlyph name="unia416" xMin="10" yMin="0" xMax="592" yMax="709">
      <contour>
        <pt x="372" y="709" on="1"/>
        <pt x="10" y="232" on="1"/>
        <pt x="10" y="157" on="1"/>
        <pt x="426" y="157" on="1"/>
        <pt x="426" y="0" on="1"/>
        <pt x="455" y="0" on="1"/>
        <pt x="455" y="157" on="1"/>
        <pt x="592" y="157" on="1"/>
        <pt x="592" y="246" on="1"/>
        <pt x="455" y="246" on="1"/>
        <pt x="455" y="709" on="1"/>
      </contour>
      <contour>
        <pt x="379" y="600" on="1"/>
        <pt x="426" y="600" on="1"/>
        <pt x="426" y="246" on="1"/>
        <pt x="80" y="246" on="1"/>
      </contour>
      <instructions/>
    </TTGlyph>

    <TTGlyph name="unia618" xMin="57" yMin="0" xMax="531" yMax="748">
      <contour>
        <pt x="322" y="748" on="1"/>
        <pt x="190" y="748" on="0"/>
        <pt x="57" y="577" on="0"/>
        <pt x="59" y="458" on="1"/>
        <pt x="145" y="458" on="1"/>
        <pt x="143" y="552" on="0"/>
        <pt x="215" y="602" on="1"/>
        <pt x="255" y="659" on="0"/>
        <pt x="307" y="662" on="1"/>
        <pt x="365" y="662" on="0"/>
        <pt x="453" y="587" on="0"/>
        <pt x="453" y="544" on="1"/>
        <pt x="453" y="454" on="0"/>
        <pt x="397" y="396" on="1"/>
        <pt x="359" y="352" on="0"/>
        <pt x="291" y="290" on="1"/>
        <pt x="161" y="232" on="0"/>
        <pt x="130" y="164" on="1"/>
        <pt x="59" y="112" on="0"/>
        <pt x="59" y="0" on="1"/>
        <pt x="531" y="0" on="1"/>
        <pt x="531" y="65" on="1"/>
        <pt x="153" y="65" on="1"/>
        <pt x="169" y="134" on="0"/>
        <pt x="304" y="229" on="1"/>
        <pt x="428" y="340" on="0"/>
        <pt x="482" y="352" on="1"/>
        <pt x="528" y="424" on="0"/>
        <pt x="528" y="622" on="0"/>
        <pt x="401" y="748" on="0"/>
      </contour>
      <instructions/>
    </TTGlyph>

    <TTGlyph name="unib218" xMin="39" yMin="-14" xMax="542" yMax="709">
      <contour>
        <pt x="115" y="709" on="1"/>
        <pt x="67" y="310" on="1"/>
        <pt x="141" y="310" on="1"/>
        <pt x="162" y="358" on="0"/>
        <pt x="224" y="396" on="1"/>
        <pt x="234" y="401" on="0"/>
        <pt x="292" y="401" on="1"/>
        <pt x="370" y="402" on="0"/>
        <pt x="481" y="340" on="0"/>
        <pt x="481" y="232" on="1"/>
        <pt x="481" y="149" on="0"/>
        <pt x="365" y="48" on="0"/>
        <pt x="286" y="48" on="1"/>
        <pt x="255" y="48" on="0"/>
        <pt x="183" y="89" on="1"/>
        <pt x="138" y="128" on="0"/>
        <pt x="145" y="197" on="1"/>
        <pt x="39" y="197" on="1"/>
        <pt x="54" y="81" on="0"/>
        <pt x="130" y="22" on="1"/>
        <pt x="224" y="-14" on="0"/>
        <pt x="292" y="-14" on="1"/>
        <pt x="397" y="-14" on="0"/>
        <pt x="482" y="50" on="1"/>
        <pt x="542" y="119" on="0"/>
        <pt x="542" y="246" on="1"/>
        <pt x="542" y="340" on="0"/>
        <pt x="422" y="459" on="0"/>
        <pt x="313" y="459" on="1"/>
        <pt x="271" y="471" on="0"/>
        <pt x="255" y="459" on="1"/>
        <pt x="182" y="437" on="0"/>
        <pt x="143" y="404" on="1"/>
        <pt x="144" y="404" on="1"/>
        <pt x="158" y="650" on="1"/>
        <pt x="509" y="650" on="1"/>
        <pt x="509" y="709" on="1"/>
      </contour>
      <instructions/>
    </TTGlyph>

    <TTGlyph name="unib471" xMin="39" yMin="-14" xMax="568" yMax="748">
      <contour>
        <pt x="292" y="748" on="1"/>
        <pt x="194" y="748" on="0"/>
        <pt x="39" y="609" on="0"/>
        <pt x="39" y="489" on="1"/>
        <pt x="39" y="368" on="0"/>
        <pt x="98" y="340" on="1"/>
        <pt x="161" y="241" on="0"/>
        <pt x="283" y="241" on="1"/>
        <pt x="330" y="264" on="0"/>
        <pt x="482" y="340" on="0"/>
        <pt x="461" y="352" on="1"/>
        <pt x="460" y="352" on="1"/>
        <pt x="457" y="324" on="1"/>
        <pt x="457" y="207" on="0"/>
        <pt x="453" y="134" on="1"/>
        <pt x="374" y="40" on="0"/>
        <pt x="292" y="40" on="1"/>
        <pt x="160" y="40" on="0"/>
        <pt x="136" y="164" on="1"/>
        <pt x="57" y="164" on="1"/>
        <pt x="86" y="-14" on="0"/>
        <pt x="282" y="-14" on="1"/>
        <pt x="426" y="-13" on="0"/>
        <pt x="468" y="112" on="1"/>
        <pt x="568" y="211" on="0"/>
        <pt x="568" y="378" on="1"/>
        <pt x="568" y="541" on="0"/>
        <pt x="501" y="622" on="1"/>
        <pt x="416" y="748" on="0"/>
      </contour>
      <contour>
        <pt x="292" y="659" on="1"/>
        <pt x="368" y="659" on="0"/>
        <pt x="422" y="602" on="1"/>
        <pt x="481" y="552" on="0"/>
        <pt x="481" y="421" on="0"/>
        <pt x="358" y="340" on="0"/>
        <pt x="292" y="340" on="1"/>
        <pt x="207" y="340" on="0"/>
        <pt x="145" y="406" on="0"/>
        <pt x="145" y="489" on="1"/>
        <pt x="145" y="547" on="0"/>
        <pt x="213" y="659" on="0"/>
      </contour>
      <instructions/>
    </TTGlyph>

    <TTGlyph name="unib632" xMin="37" yMin="-14" xMax="560" yMax="748">
      <contour>
        <pt x="292" y="748" on="1"/>
        <pt x="182" y="748" on="0"/>
        <pt x="110" y="678" on="1"/>
        <pt x="67" y="602" on="0"/>
        <pt x="67" y="558" on="1"/>
        <pt x="67" y="480" on="0"/>
        <pt x="82" y="431" on="1"/>
        <pt x="144" y="386" on="0"/>
        <pt x="182" y="378" on="1"/>
        <pt x="182" y="379" on="1"/>
        <pt x="111" y="361" on="0"/>
        <pt x="69" y="340" on="1"/>
        <pt x="37" y="275" on="0"/>
        <pt x="37" y="197" on="1"/>
        <pt x="37" y="112" on="0"/>
        <pt x="182" y="-14" on="0"/>
        <pt x="426" y="-14" on="0"/>
        <pt x="482" y="43" on="1"/>
        <pt x="560" y="112" on="0"/>
        <pt x="560" y="197" on="1"/>
        <pt x="560" y="275" on="0"/>
        <pt x="501" y="340" on="1"/>
        <pt x="465" y="361" on="0"/>
        <pt x="416" y="379" on="1"/>
        <pt x="416" y="378" on="1"/>
        <pt x="470" y="386" on="0"/>
        <pt x="501" y="431" on="1"/>
        <pt x="529" y="480" on="0"/>
        <pt x="529" y="558" on="1"/>
        <pt x="529" y="602" on="0"/>
        <pt x="462" y="678" on="1"/>
        <pt x="453" y="748" on="0"/>
      </contour>
      <contour>
        <pt x="292" y="649" on="1"/>
        <pt x="374" y="649" on="0"/>
        <pt x="414" y="615" on="1"/>
        <pt x="461" y="609" on="0"/>
        <pt x="461" y="480" on="0"/>
        <pt x="426" y="447" on="1"/>
        <pt x="426" y="406" on="0"/>
        <pt x="218" y="406" on="0"/>
        <pt x="177" y="447" on="1"/>
        <pt x="136" y="480" on="0"/>
        <pt x="136" y="609" on="0"/>
        <pt x="170" y="615" on="1"/>
        <pt x="213" y="649" on="0"/>
      </contour>
      <contour>
        <pt x="292" y="363" on="1"/>
        <pt x="384" y="363" on="0"/>
        <pt x="424" y="288" on="1"/>
        <pt x="465" y="264" on="0"/>
        <pt x="465" y="134" on="0"/>
        <pt x="424" y="86" on="1"/>
        <pt x="377" y="43" on="0"/>
        <pt x="199" y="43" on="0"/>
        <pt x="111" y="134" on="0"/>
        <pt x="111" y="264" on="0"/>
        <pt x="162" y="288" on="1"/>
        <pt x="199" y="363" on="0"/>
      </contour>
      <instructions/>
    </TTGlyph>

    <TTGlyph name="unic541" xMin="105" yMin="0" xMax="356" yMax="709">
      <contour>
        <pt x="298" y="709" on="1"/>
        <pt x="247" y="662" on="0"/>
        <pt x="160" y="597" on="0"/>
        <pt x="105" y="592" on="1"/>
        <pt x="105" y="517" on="1"/>
        <pt x="208" y="535" on="0"/>
        <pt x="278" y="622" on="1"/>
        <pt x="278" y="0" on="1"/>
        <pt x="356" y="0" on="1"/>
        <pt x="356" y="709" on="1"/>
      </contour>
      <instructions/>
    </TTGlyph>

    <TTGlyph name="unie478" xMin="39" yMin="-14" xMax="568" yMax="769">
      <contour>
        <pt x="322" y="748" on="1"/>
        <pt x="182" y="748" on="0"/>
        <pt x="118" y="609" on="1"/>
        <pt x="39" y="502" on="0"/>
        <pt x="39" y="324" on="1"/>
        <pt x="39" y="191" on="0"/>
        <pt x="111" y="89" on="1"/>
        <pt x="182" y="-13" on="0"/>
        <pt x="307" y="-14" on="1"/>
        <pt x="453" y="-13" on="0"/>
        <pt x="568" y="145" on="0"/>
        <pt x="568" y="348" on="0"/>
        <pt x="482" y="483" on="0"/>
        <pt x="322" y="483" on="1"/>
        <pt x="271" y="483" on="0"/>
        <pt x="208" y="440" on="1"/>
        <pt x="148" y="401" on="0"/>
        <pt x="127" y="352" on="1"/>
        <pt x="145" y="352" on="1"/>
        <pt x="121" y="378" on="1"/>
        <pt x="121" y="544" on="0"/>
        <pt x="177" y="577" on="1"/>
        <pt x="224" y="678" on="0"/>
        <pt x="307" y="659" on="1"/>
        <pt x="432" y="678" on="0"/>
        <pt x="481" y="544" on="1"/>
        <pt x="531" y="544" on="1"/>
        <pt x="503" y="769" on="0"/>
      </contour>
      <contour>
        <pt x="307" y="397" on="1"/>
        <pt x="379" y="402" on="0"/>
        <pt x="482" y="352" on="1"/>
        <pt x="482" y="307" on="0"/>
        <pt x="482" y="154" on="0"/>
        <pt x="453" y="109" on="1"/>
        <pt x="383" y="48" on="0"/>
        <pt x="307" y="40" on="1"/>
        <pt x="255" y="40" on="0"/>
        <pt x="182" y="112" on="1"/>
        <pt x="136" y="163" on="0"/>
        <pt x="136" y="290" on="0"/>
        <pt x="234" y="397" on="0"/>
      </contour>
      <instructions/>
    </TTGlyph>

    <TTGlyph name="unie825" xMin="39" yMin="-14" xMax="568" yMax="748">
      <contour>
        <pt x="307" y="748" on="1"/>
        <pt x="218" y="748" on="0"/>
        <pt x="133" y="678" on="1"/>
        <pt x="81" y="597" on="0"/>
        <pt x="76" y="507" on="1"/>
        <pt x="138" y="507" on="1"/>
        <pt x="155" y="571" on="0"/>
        <pt x="251" y="662" on="0"/>
        <pt x="305" y="650" on="1"/>
        <pt x="370" y="662" on="0"/>
        <pt x="413" y="615" on="1"/>
        <pt x="482" y="609" on="0"/>
        <pt x="482" y="459" on="0"/>
        <pt x="383" y="401" on="0"/>
        <pt x="307" y="401" on="1"/>
        <pt x="247" y="401" on="1"/>
        <pt x="247" y="328" on="1"/>
        <pt x="322" y="328" on="1"/>
        <pt x="383" y="328" on="0"/>
        <pt x="481" y="287" on="0"/>
        <pt x="481" y="142" on="0"/>
        <pt x="482" y="95" on="1"/>
        <pt x="383" y="48" on="0"/>
        <pt x="329" y="48" on="1"/>
        <pt x="233" y="47" on="0"/>
        <pt x="190" y="109" on="1"/>
        <pt x="127" y="142" on="0"/>
        <pt x="144" y="232" on="1"/>
        <pt x="39" y="232" on="1"/>
        <pt x="50" y="112" on="0"/>
        <pt x="133" y="25" on="1"/>
        <pt x="208" y="-13" on="0"/>
        <pt x="329" y="-14" on="1"/>
        <pt x="422" y="-14" on="0"/>
        <pt x="568" y="101" on="0"/>
        <pt x="568" y="197" on="1"/>
        <pt x="568" y="270" on="0"/>
        <pt x="512" y="340" on="1"/>
        <pt x="470" y="351" on="0"/>
        <pt x="428" y="369" on="1"/>
        <pt x="541" y="401" on="0"/>
        <pt x="541" y="544" on="1"/>
        <pt x="541" y="624" on="0"/>
        <pt x="428" y="748" on="0"/>
      </contour>
      <instructions/>
    </TTGlyph>

    <TTGlyph name="unif129" xMin="57" yMin="-14" xMax="568" yMax="769">
      <contour>
        <pt x="292" y="748" on="1"/>
        <pt x="162" y="769" on="0"/>
        <pt x="111" y="609" on="1"/>
        <pt x="57" y="544" on="0"/>
        <pt x="57" y="193" on="0"/>
        <pt x="111" y="111" on="1"/>
        <pt x="162" y="-14" on="0"/>
        <pt x="422" y="-14" on="0"/>
        <pt x="512" y="111" on="1"/>
        <pt x="568" y="193" on="0"/>
        <pt x="568" y="544" on="0"/>
        <pt x="512" y="609" on="1"/>
        <pt x="422" y="769" on="0"/>
      </contour>
      <contour>
        <pt x="292" y="662" on="1"/>
        <pt x="388" y="662" on="0"/>
        <pt x="428" y="544" on="1"/>
        <pt x="482" y="489" on="0"/>
        <pt x="482" y="246" on="0"/>
        <pt x="428" y="151" on="1"/>
        <pt x="388" y="47" on="0"/>
        <pt x="215" y="47" on="0"/>
        <pt x="148" y="151" on="1"/>
        <pt x="145" y="246" on="0"/>
        <pt x="145" y="489" on="0"/>
        <pt x="148" y="544" on="1"/>
        <pt x="215" y="662" on="0"/>
      </contour>
      <instructions/>
    </TTGlyph>

    <TTGlyph name="unif254" xMin="76" yMin="0" xMax="541" yMax="709">
      <contour>
        <pt x="76" y="709" on="1"/>
        <pt x="76" y="633" on="1"/>
        <pt x="440" y="633" on="1"/>
        <pt x="180" y="0" on="1"/>
        <pt x="271" y="0" on="1"/>
        <pt x="541" y="638" on="1"/>
        <pt x="541" y="709" on="1"/>
      </contour>
      <instructions/>
    </TTGlyph>

  </glyf>

  <name>
    <namerecord nameID="0" platformID="1" platEncID="0" langID="0x0" unicode="True">
      Created by font-carrier
    </namerecord>
    <namerecord nameID="1" platformID="1" platEncID="0" langID="0x0" unicode="True">
      .PingFang SC
    </namerecord>
    <namerecord nameID="2" platformID="1" platEncID="0" langID="0x0" unicode="True">
      Regular
    </namerecord>
    <namerecord nameID="3" platformID="1" platEncID="0" langID="0x0" unicode="True">
      .PingFang-SC-Regular
    </namerecord>
    <namerecord nameID="4" platformID="1" platEncID="0" langID="0x0" unicode="True">
      .PingFang-SC-Regular
    </namerecord>
    <namerecord nameID="5" platformID="1" platEncID="0" langID="0x0" unicode="True">
      Version 1.0
    </namerecord>
    <namerecord nameID="6" platformID="1" platEncID="0" langID="0x0" unicode="True">
      .PingFang-SC-Regular
    </namerecord>
    <namerecord nameID="10" platformID="1" platEncID="0" langID="0x0" unicode="True">
      Generated by svg2ttf from Fontello project.
    </namerecord>
    <namerecord nameID="11" platformID="1" platEncID="0" langID="0x0" unicode="True">
      http://fontello.com
    </namerecord>
    <namerecord nameID="0" platformID="3" platEncID="1" langID="0x409">
      Created by font-carrier
    </namerecord>
    <namerecord nameID="1" platformID="3" platEncID="1" langID="0x409">
      .PingFang SC
    </namerecord>
    <namerecord nameID="2" platformID="3" platEncID="1" langID="0x409">
      Regular
    </namerecord>
    <namerecord nameID="3" platformID="3" platEncID="1" langID="0x409">
      .PingFang-SC-Regular
    </namerecord>
    <namerecord nameID="4" platformID="3" platEncID="1" langID="0x409">
      .PingFang-SC-Regular
    </namerecord>
    <namerecord nameID="5" platformID="3" platEncID="1" langID="0x409">
      Version 1.0
    </namerecord>
    <namerecord nameID="6" platformID="3" platEncID="1" langID="0x409">
      .PingFang-SC-Regular
    </namerecord>
    <namerecord nameID="10" platformID="3" platEncID="1" langID="0x409">
      Generated by svg2ttf from Fontello project.
    </namerecord>
    <namerecord nameID="11" platformID="3" platEncID="1" langID="0x409">
      http://fontello.com
    </namerecord>
  </name>

  <post>
    <formatType value="2.0"/>
    <italicAngle value="0.0"/>
    <underlinePosition value="14"/>
    <underlineThickness value="0"/>
    <isFixedPitch value="0"/>
    <minMemType42 value="0"/>
    <maxMemType42 value="0"/>
    <minMemType1 value="0"/>
    <maxMemType1 value="11"/>
    <psNames>
      <!-- This file uses unique glyph names based on the information
           found in the 'post' table. Since these names might not be unique,
           we have to invent artificial names in case of clashes. In order to
           be able to retain the original information, we need a name to
           ps name mapping for those cases where they differ. That's what
           you see below.
            -->
    </psNames>
    <extraNames>
      <!-- following are the name that are not taken from the standard Mac glyph order -->
      <psName name="unib471"/>
      <psName name="unia416"/>
      <psName name="unie825"/>
      <psName name="unib218"/>
      <psName name="unib632"/>
      <psName name="unic541"/>
      <psName name="unif254"/>
      <psName name="unia618"/>
      <psName name="unif129"/>
      <psName name="unie478"/>
    </extraNames>
  </post>

</ttFont>
